pytorch_widedeep/__init__.py
pytorch_widedeep/callbacks.py
pytorch_widedeep/dataloaders.py
pytorch_widedeep/initializers.py
pytorch_widedeep/losses.py
pytorch_widedeep/losses_multitarget.py
pytorch_widedeep/metrics.py
pytorch_widedeep/tab2vec.py
pytorch_widedeep/version.py
pytorch_widedeep/wdtypes.py
pytorch_widedeep/bayesian_models/__init__.py
pytorch_widedeep/bayesian_models/_base_bayesian_model.py
pytorch_widedeep/bayesian_models/_weight_sampler.py
pytorch_widedeep/bayesian_models/bayesian_nn/__init__.py
pytorch_widedeep/bayesian_models/bayesian_nn/modules/__init__.py
pytorch_widedeep/bayesian_models/bayesian_nn/modules/bayesian_embedding.py
pytorch_widedeep/bayesian_models/bayesian_nn/modules/bayesian_linear.py
pytorch_widedeep/bayesian_models/tabular/__init__.py
pytorch_widedeep/bayesian_models/tabular/bayesian_embeddings_layers.py
pytorch_widedeep/bayesian_models/tabular/bayesian_linear/__init__.py
pytorch_widedeep/bayesian_models/tabular/bayesian_linear/bayesian_wide.py
pytorch_widedeep/bayesian_models/tabular/bayesian_mlp/__init__.py
pytorch_widedeep/bayesian_models/tabular/bayesian_mlp/_layers.py
pytorch_widedeep/bayesian_models/tabular/bayesian_mlp/bayesian_tab_mlp.py
pytorch_widedeep/datasets/__init__.py
pytorch_widedeep/datasets/_base.py
pytorch_widedeep/datasets/data/MovieLens100k_data.parquet.brotli
pytorch_widedeep/datasets/data/MovieLens100k_items.parquet.brotli
pytorch_widedeep/datasets/data/MovieLens100k_users.parquet.brotli
pytorch_widedeep/datasets/data/WomensClothingE-CommerceReviews.parquet.brotli
pytorch_widedeep/datasets/data/__init__.py
pytorch_widedeep/datasets/data/adult.parquet.brotli
pytorch_widedeep/datasets/data/bio_train.parquet.brotli
pytorch_widedeep/datasets/data/birds_test.parquet.brotli
pytorch_widedeep/datasets/data/birds_train.parquet.brotli
pytorch_widedeep/datasets/data/california_housing.parquet.brotli
pytorch_widedeep/datasets/data/ecoli.parquet.brotli
pytorch_widedeep/datasets/data/rf1_test.parquet.brotli
pytorch_widedeep-1.7.0.dist-info/licenses/LICENSE_APACHE_v2_0
pytorch_widedeep-1.7.0.dist-info/licenses/LICENSE_MIT
pytorch_widedeep-1.7.0.dist-info/METADATA
pytorch_widedeep-1.7.0.dist-info/WHEEL
pytorch_widedeep-1.7.0.dist-info/top_level.txt
pytorch_widedeep-1.7.0.dist-info/zip-safe
pytorch_widedeep-1.7.0.dist-info/RECORD
