Metadata-Version: 2.4
Name: pytorch-widedeep
Version: 1.7.0
Summary: Combine tabular data with text and images using Wide and Deep models in Pytorch
Home-page: https://github.com/jrzaurin/pytorch-widedeep
Author: Javier Rodriguez Zaurin
Author-email: jrzaurin@gmail.com
License: MIT
Classifier: Development Status :: 5 - Production/Stable
Classifier: Environment :: Other Environment
Classifier: Framework :: Jupyter
Classifier: Intended Audience :: Science/Research
Classifier: License :: OSI Approved :: MIT License
Classifier: Natural Language :: English
Classifier: Operating System :: OS Independent
Classifier: Programming Language :: Python
Classifier: Topic :: Scientific/Engineering :: Artificial Intelligence
Requires-Python: >=3.9.0
License-File: LICENSE_APACHE_v2_0
License-File: LICENSE_MIT
Requires-Dist: scipy>=1.7.3
Requires-Dist: numpy<2.0.0,>=1.21.6
Requires-Dist: pandas>=1.3.5
Requires-Dist: scikit-learn>=1.0.2
Requires-Dist: gensim
Requires-Dist: spacy
Requires-Dist: opencv-contrib-python>=4.9.0.80
Requires-Dist: tqdm
Requires-Dist: torch>=2.0.0
Requires-Dist: torchvision>=0.15.0
Requires-Dist: einops
Requires-Dist: wrapt
Requires-Dist: torchmetrics>=1.3.1
Requires-Dist: pyarrow>=15.0.0
Requires-Dist: fastparquet>=2024.2.0
Requires-Dist: transformers>=4.37.0
Requires-Dist: sentence-transformers>=2.3.0
Requires-Dist: sentencepiece>=0.2.0
Provides-Extra: test
Requires-Dist: pytest; extra == "test"
Requires-Dist: pytest-cov; extra == "test"
Requires-Dist: codecov; extra == "test"
Requires-Dist: faker; extra == "test"
Provides-Extra: docs
Requires-Dist: sphinx; extra == "docs"
Requires-Dist: sphinx_rtd_theme; extra == "docs"
Requires-Dist: recommonmark; extra == "docs"
Requires-Dist: sphinx-markdown-tables; extra == "docs"
Requires-Dist: sphinx-copybutton; extra == "docs"
Requires-Dist: sphinx-autodoc-typehints; extra == "docs"
Provides-Extra: mkdocs
Requires-Dist: mkdocs; extra == "mkdocs"
Requires-Dist: mkdocs-material; extra == "mkdocs"
Requires-Dist: mkdocs-autolinks-plugin; extra == "mkdocs"
Requires-Dist: mkdocs-git-authors-plugin; extra == "mkdocs"
Requires-Dist: mkdocs-jupyter; extra == "mkdocs"
Requires-Dist: mkdocstrings; extra == "mkdocs"
Requires-Dist: mkdocstrings-python; extra == "mkdocs"
Provides-Extra: quality
Requires-Dist: black; extra == "quality"
Requires-Dist: isort; extra == "quality"
Requires-Dist: flake8; extra == "quality"
Provides-Extra: all
Requires-Dist: pytest; extra == "all"
Requires-Dist: pytest-cov; extra == "all"
Requires-Dist: codecov; extra == "all"
Requires-Dist: faker; extra == "all"
Requires-Dist: sphinx; extra == "all"
Requires-Dist: sphinx_rtd_theme; extra == "all"
Requires-Dist: recommonmark; extra == "all"
Requires-Dist: sphinx-markdown-tables; extra == "all"
Requires-Dist: sphinx-copybutton; extra == "all"
Requires-Dist: sphinx-autodoc-typehints; extra == "all"
Requires-Dist: black; extra == "all"
Requires-Dist: isort; extra == "all"
Requires-Dist: flake8; extra == "all"
Requires-Dist: mkdocs; extra == "all"
Requires-Dist: mkdocs-material; extra == "all"
Requires-Dist: mkdocs-autolinks-plugin; extra == "all"
Requires-Dist: mkdocs-git-authors-plugin; extra == "all"
Requires-Dist: mkdocs-jupyter; extra == "all"
Requires-Dist: mkdocstrings; extra == "all"
Requires-Dist: mkdocstrings-python; extra == "all"
Dynamic: author
Dynamic: author-email
Dynamic: classifier
Dynamic: description
Dynamic: description-content-type
Dynamic: home-page
Dynamic: license
Dynamic: license-file
Dynamic: provides-extra
Dynamic: requires-dist
Dynamic: requires-python
Dynamic: summary
